{
   "wallpapers": [

       {
         "author": "Unknown",
         "url": "https://raw.githubusercontent.com/EdzonDM/InsWall-Walls/master/Colecciones/Heroes/Captain%20America.jpg",
         "name": "Captain America",
         "thumbnail": "https://raw.githubusercontent.com/EdzonDM/InsWall-Walls/master/Colecciones/Heroes/Preview/Captain%20Preview.jpg",
         "website": "http://dereklaufman.deviantart.com/gallery",
         "categoria": "Hero",
         "resolucion": "1080 x 1920",
         "tamaño": "168 KB",
         "fecha": "3 jan. 2017"   
       },
       
       {
         "author": "Unknown",
         "url": "https://raw.githubusercontent.com/EdzonDM/InsWall-Walls/master/Colecciones/Heroes/Iron%20Man.jpg",
         "name": "Iron Man",
         "thumbnail": "https://raw.githubusercontent.com/EdzonDM/InsWall-Walls/master/Colecciones/Heroes/Preview/Iron%20Man%20Preview.jpg",
         "website": "http://dereklaufman.deviantart.com/gallery",
         "categoria": "Hero",
         "resolucion": "1080 x 1920",
         "tamaño": "70 KB",
         "fecha": "3 jan. 2017"   
       },
       
       {
         "author": "Derek Laufman",
         "url": "https://raw.githubusercontent.com/EdzonDM/InsWall-Walls/master/Colecciones/Heroes/Spider%20Girl%20v2.jpg",
         "name": "Spider Girl",
         "thumbnail": "https://raw.githubusercontent.com/EdzonDM/InsWall-Walls/master/Colecciones/Heroes/Preview/Spider%20Girl%20v2%20Preview.jpg",
         "website": "http://dereklaufman.deviantart.com/gallery",
         "categoria": "Hero",
         "resolucion": "1080 x 1920",
         "tamaño": "573 KB",
         "fecha": "3 jan. 2017"   
       } ,      
       
       {
         "author": "Derek Laufman",
         "url": "https://raw.githubusercontent.com/EdzonDM/InsWall-Walls/master/Colecciones/Heroes/Spider%20Man%20v2.jpg",
         "name": "Spider Man",
         "thumbnail": "https://raw.githubusercontent.com/EdzonDM/InsWall-Walls/master/Colecciones/Heroes/Preview/Spider%20Man%20v2%20Preview.jpg",
         "website": "http://dereklaufman.deviantart.com/gallery",
         "categoria": "Hero",
         "resolucion": "1080 x 1920",
         "tamaño": "612 KB",
         "fecha": "3 jan. 2017"   
       },    
            
        {
         "author": "Derek Laufman",
         "url": "https://raw.githubusercontent.com/EdzonDM/InsWall-Walls/master/Colecciones/Heroes/Wolverine%20v2.jpg",
         "name": "Wolverine",
         "thumbnail": "https://raw.githubusercontent.com/EdzonDM/InsWall-Walls/master/Colecciones/Heroes/Preview/Wolverine%20v2%20Preview.jpg",
         "website": "http://dereklaufman.deviantart.com/gallery",
         "categoria": "Hero",
         "resolucion": "1080 x 1920",
         "tamaño": "650 KB",
         "fecha": "3 jan. 2017"   
       },    
       
       {
         "author": "Derek Laufman",
         "url": "https://raw.githubusercontent.com/EdzonDM/InsWall-Walls/master/Colecciones/Heroes/Deadpool%20v2.jpg",
         "name": "Deadpool",
         "thumbnail": "https://raw.githubusercontent.com/EdzonDM/InsWall-Walls/master/Colecciones/Heroes/Preview/Deadpool%20v2%20Preview.jpg",
         "website": "http://dereklaufman.deviantart.com/gallery",
         "categoria": "Hero",
         "resolucion": "1080 x 1920",
         "tamaño": "628 KB",
         "fecha": "3 jan. 2017"   
       },    
             
       
       {
         "author": "Derek Laufman",
         "url": "https://raw.githubusercontent.com/EdzonDM/InsWall-Walls/master/Colecciones/Heroes/Captain%20America%20v2.jpg",
         "name": "Captain America",
         "thumbnail": "https://raw.githubusercontent.com/EdzonDM/InsWall-Walls/master/Colecciones/Heroes/Preview/Captain%20America%20v2%20Preview.jpg",
         "website": "http://dereklaufman.deviantart.com/gallery",
         "categoria": "Hero",
         "resolucion": "1080 x 1920",
         "tamaño": "701 KB",
         "fecha": "3 jan. 2017"   
       } ,      
       
       {
         "author": "Derek Laufman",
         "url": "https://raw.githubusercontent.com/EdzonDM/InsWall-Walls/master/Colecciones/Heroes/Batman%20v2.jpg",
         "name": "Batman",
         "thumbnail": "https://raw.githubusercontent.com/EdzonDM/InsWall-Walls/master/Colecciones/Heroes/Preview/Batman%20v2%20Preview.jpg",
         "website": "http://dereklaufman.deviantart.com/gallery",
         "categoria": "Hero",
         "resolucion": "1080 x 1920",
         "tamaño": "623 KB",
         "fecha": "3 jan. 2017"   
       },    
       
       {
         "author": "Derek Laufman",
         "url": "https://raw.githubusercontent.com/EdzonDM/InsWall-Walls/master/Colecciones/Heroes/Venom%20v2.jpg",
         "name": "Venom",
         "thumbnail": "https://raw.githubusercontent.com/EdzonDM/InsWall-Walls/master/Colecciones/Heroes/Preview/Venom%20v2%20Preview.jpg",
         "website": "http://dereklaufman.deviantart.com/gallery",
         "categoria": "Hero",
         "resolucion": "1080 x 1920",
         "tamaño": "650 KB",
         "fecha": "3 jan. 2017"   
       },    
       
       {
         "author": "Derek Laufman",
         "url": "https://raw.githubusercontent.com/EdzonDM/InsWall-Walls/master/Colecciones/Heroes/Panther%20v2.jpg",
         "name": "Panther",
         "thumbnail": "https://raw.githubusercontent.com/EdzonDM/InsWall-Walls/master/Colecciones/Heroes/Preview/Panther%20v2%20Preview.jpg",
         "website": "http://dereklaufman.deviantart.com/gallery",
         "categoria": "Hero",
         "resolucion": "1080 x 1920",
         "tamaño": "647 KB",
         "fecha": "3 jan. 2017"   
       } ,             
       
       {
         "author": "Derek Laufman",
         "url": "https://raw.githubusercontent.com/EdzonDM/InsWall-Walls/master/Colecciones/Heroes/Hellboy%20v2.jpg",
         "name": "Hellboy",
         "thumbnail": "https://raw.githubusercontent.com/EdzonDM/InsWall-Walls/master/Colecciones/Heroes/Preview/Hellboy%20v2%20Preview.jpg",
         "website": "http://dereklaufman.deviantart.com/gallery",
         "categoria": "Hero",
         "resolucion": "1080 x 1920",
         "tamaño": "671 KB",
         "fecha": "3 jan. 2017"   
       },    
             
       
       {
         "author": "Derek Laufman",
         "url": "https://raw.githubusercontent.com/EdzonDM/InsWall-Walls/master/Colecciones/Heroes/Harley%20Quinn%20v2.jpg",
         "name": "Harley Quinn",
         "thumbnail": "https://raw.githubusercontent.com/EdzonDM/InsWall-Walls/master/Colecciones/Heroes/Preview/Harley%20Quinn%20v2%20Preview.jpg",
         "website": "http://dereklaufman.deviantart.com/gallery",
         "categoria": "Hero",
         "resolucion": "1080 x 1920",
         "tamaño": "714 KB",
         "fecha": "3 jan. 2017"   
       } ,      
       
       {
         "author": "Derek Laufman",
         "url": "https://raw.githubusercontent.com/EdzonDM/InsWall-Walls/master/Colecciones/Heroes/Yoda%20v2.jpg",
         "name": "Yoda",
         "thumbnail": "https://raw.githubusercontent.com/EdzonDM/InsWall-Walls/master/Colecciones/Heroes/Preview/Yoda%20v2%20Preview.jpg",
         "website": "http://dereklaufman.deviantart.com/gallery",
         "categoria": "Hero",
         "resolucion": "1080 x 1920",
         "tamaño": "579 KB",
         "fecha": "3 jan. 2017"   
       },  
       
       {
         "author": "Derek Laufman",
         "url": "https://raw.githubusercontent.com/EdzonDM/InsWall-Walls/master/Colecciones/Heroes/Darth%20Vader%20v2.jpg",
         "name": "Darth Vader",
         "thumbnail": "https://raw.githubusercontent.com/EdzonDM/InsWall-Walls/master/Colecciones/Heroes/Preview/Darth%20Vader%20v2%20Preview.jpg",
         "website": "http://dereklaufman.deviantart.com/gallery",
         "categoria": "Hero",
         "resolucion": "1080 x 1920",
         "tamaño": "701 KB",
         "fecha": "3 jan. 2017"   
       }, 
       
     {
         "author": "Sudipto",
         "url": "https://raw.githubusercontent.com/EdzonDM/InsWall-Walls/master/Colecciones/Heroes/Captain%20America%20V1.jpg",
         "name": "Captain America",
         "thumbnail": "https://raw.githubusercontent.com/EdzonDM/InsWall-Walls/master/Colecciones/Heroes/Preview/Captain%20America%20V1%20Preview.jpg",
         "website": "",
         "categoria": "Hero",
         "resolucion": "1080 x 1920",
         "tamaño": "142 KB",
         "fecha": "18 dic. 2016"   
       } ,      
       
       {
         "author": "Sudipto",
         "url": "https://raw.githubusercontent.com/EdzonDM/InsWall-Walls/master/Colecciones/Heroes/Iron%20Man%20V1.jpg",
         "name": "Iron Man",
         "thumbnail": "https://raw.githubusercontent.com/EdzonDM/InsWall-Walls/master/Colecciones/Heroes/Preview/Iron%20Man%20V1%20Preview.jpg",
         "website": "",
         "categoria": "Hero",
         "resolucion": "1080 x 1920",
         "tamaño": "308 KB",
         "fecha": "18 dic. 2016"   
       },     
       
       {
         "author": "Sudipto",
         "url": "https://raw.githubusercontent.com/EdzonDM/InsWall-Walls/master/Colecciones/Heroes/Spider%20Man%20V1.jpg",
         "name": "Spider Man",
         "thumbnail": "https://raw.githubusercontent.com/EdzonDM/InsWall-Walls/master/Colecciones/Heroes/Preview/Spider%20Man%20V1%20Preview.jpg",
         "website": "",
         "categoria": "Hero",
         "resolucion": "1080 x 1920",
         "tamaño": "201 KB",
         "fecha": "18 dic. 2016"   
       },   
       
        {
         "author": "Sudipto",
         "url": "https://raw.githubusercontent.com/EdzonDM/InsWall-Walls/master/Colecciones/Heroes/Green%20Arrow%20V1.jpg",
         "name": "Green Arrow",
         "thumbnail": "https://raw.githubusercontent.com/EdzonDM/InsWall-Walls/master/Colecciones/Heroes/Preview/Green%20Arrow%20V1%20Preview.jpg",
         "website": "",
         "categoria": "Hero",
         "resolucion": "1080 x 1920",
         "tamaño": "201 KB",
         "fecha": "18 dic. 2016"   
       } , 
       
       {
         "author": "Sudipto",
         "url": "https://raw.githubusercontent.com/EdzonDM/InsWall-Walls/master/Colecciones/Heroes/Flash%20V1.jpg",
         "name": "Flash",
         "thumbnail": "https://raw.githubusercontent.com/EdzonDM/InsWall-Walls/master/Colecciones/Heroes/Preview/Flash%20V1%20Preview.jpg",
         "website": "",
         "categoria": "Hero",
         "resolucion": "1080 x 1920",
         "tamaño": "173 KB",
         "fecha": "18 dic. 2016"   
       },       
       
       {
         "author": "Sudipto",
         "url": "https://raw.githubusercontent.com/EdzonDM/InsWall-Walls/master/Colecciones/Heroes/Batman%20V1.jpg",
         "name": "Batman",
         "thumbnail": "https://raw.githubusercontent.com/EdzonDM/InsWall-Walls/master/Colecciones/Heroes/Preview/Batman%20V1%20Preview.jpg",
         "website": "",
         "categoria": "Hero",
         "resolucion": "1080 x 1920",
         "tamaño": "109 KB",
         "fecha": "18 dic. 2016"   
       } ,  
       
       {
         "author": "Unknown",
         "url": "https://raw.githubusercontent.com/EdzonDM/InsWall-Walls/master/Colecciones/Heroes/Batman.jpg",
         "name": "Batman",
         "thumbnail": "https://raw.githubusercontent.com/EdzonDM/InsWall-Walls/master/Colecciones/Heroes/Preview/Batman%20Preview.jpg",
         "website": "",
         "categoria": "Hero",
         "resolucion": "1080 x 1920",
         "tamaño": "463 KB",
         "fecha": "18 dic. 2016"   
       },         
  
       {
         "author": "Unknown",
         "url": "https://raw.githubusercontent.com/EdzonDM/InsWall-Walls/master/Colecciones/Heroes/Spider%20Woman.jpg",
         "name": "Spider Woman",
         "thumbnail": "https://raw.githubusercontent.com/EdzonDM/InsWall-Walls/master/Colecciones/Heroes/Preview/Spider%20Woman%20Preview.jpg",
         "website": "",
         "categoria": "Hero",
         "resolucion": "1080 x 1920",
         "tamaño": "178 KB",
         "fecha": "18 dic. 2016"   
        },
  
       {
         "author": "Unknown",
         "url": "https://raw.githubusercontent.com/EdzonDM/InsWall-Walls/master/Colecciones/Heroes/Avengers.jpg",
         "name": "Avengers",
         "thumbnail": "https://raw.githubusercontent.com/EdzonDM/InsWall-Walls/master/Colecciones/Heroes/Preview/Avengers%20Preview.jpg",
         "website": "",
         "categoria": "Hero",
         "resolucion": "640 x 1136",
         "tamaño": "130 KB",
         "fecha": "18 dic. 2016"   
       },
       
        {
         "author": "Unknown",
         "url": "https://raw.githubusercontent.com/EdzonDM/InsWall-Walls/master/Colecciones/Heroes/Superman%20Logo.jpg",
         "name": "Superman",
         "thumbnail": "https://raw.githubusercontent.com/EdzonDM/InsWall-Walls/master/Colecciones/Heroes/Preview/Superman%20Logo%20Preview.jpg",
         "website": "",
         "categoria": "Hero",
         "resolucion": "1080 x 1920",
         "tamaño": "97 KB",
         "fecha": "18 dic. 2016"   
       },
 
       {
         "author": "BossLogic",
         "url": "https://raw.githubusercontent.com/EdzonDM/InsWall-Walls/master/Colecciones/Heroes/Superman.png",
         "name": "Superman",
         "thumbnail": "https://raw.githubusercontent.com/EdzonDM/InsWall-Walls/master/Colecciones/Heroes/Preview/Superman%20Preview.jpg",
         "website": "https://www.behance.net/gallery/37661063/PopHead-Shots",
         "categoria": "Hero",
         "resolucion": "1440 x 2560",
         "tamaño": "182 KB",
         "fecha": "18 dic. 2016"   
       },
       
       {
         "author": "BossLogic",
         "url": "https://raw.githubusercontent.com/EdzonDM/InsWall-Walls/master/Colecciones/Heroes/Sub%20Zero.png",
         "name": "Sub Zero",
         "thumbnail": "https://raw.githubusercontent.com/EdzonDM/InsWall-Walls/master/Colecciones/Heroes/Preview/Sub%20Zero%20Preview.jpg",
         "website": "https://www.behance.net/gallery/37661063/PopHead-Shots",
         "categoria": "Hero",
         "resolucion": "1440 x 2560",
         "tamaño": "211 KB",
         "fecha": "18 dic. 2016"   
       },    
       
       {
         "author": "BossLogic",
         "url": "https://raw.githubusercontent.com/EdzonDM/InsWall-Walls/master/Colecciones/Heroes/Nova.png",
         "name": "Nova",
         "thumbnail": "https://raw.githubusercontent.com/EdzonDM/InsWall-Walls/master/Colecciones/Heroes/Preview/Nova%20Preview.jpg",
         "website": "https://www.behance.net/gallery/37661063/PopHead-Shots",
         "categoria": "Hero",
         "resolucion": "1440 x 2560",
         "tamaño": "284 KB",
         "fecha": "18 dic. 2016"   
       },    
             
       
       {
         "author": "BossLogic",
         "url": "https://raw.githubusercontent.com/EdzonDM/InsWall-Walls/master/Colecciones/Heroes/Inj%20Bat.png",
         "name": "Inj Bat",
         "thumbnail": "https://raw.githubusercontent.com/EdzonDM/InsWall-Walls/master/Colecciones/Heroes/Preview/Inj%20Bat%20Preview.jpg",
         "website": "https://www.behance.net/gallery/37661063/PopHead-Shots",
         "categoria": "Hero",
         "resolucion": "1440 x 2560",
         "tamaño": "202 KB",
         "fecha": "18 dic. 2016"   
       } ,      
       
       {
         "author": "BossLogic",
         "url": "https://raw.githubusercontent.com/EdzonDM/InsWall-Walls/master/Colecciones/Heroes/War%20Machine.png",
         "name": "War Machine",
         "thumbnail": "https://raw.githubusercontent.com/EdzonDM/InsWall-Walls/master/Colecciones/Heroes/Preview/War%20Machine%20Preview.jpg",
         "website": "https://www.behance.net/gallery/37661063/PopHead-Shots",
         "categoria": "Hero",
         "resolucion": "1440 x 2560",
         "tamaño": "244 KB",
         "fecha": "18 dic. 2016"   
       },    
       
       {
         "author": "BossLogic",
         "url": "https://raw.githubusercontent.com/EdzonDM/InsWall-Walls/master/Colecciones/Heroes/Wolverine.png",
         "name": "Wolverine",
         "thumbnail": "https://raw.githubusercontent.com/EdzonDM/InsWall-Walls/master/Colecciones/Heroes/Preview/Wolverine2%20Preview.jpg",
         "website": "https://www.behance.net/gallery/37661063/PopHead-Shots",
         "categoria": "Hero",
         "resolucion": "1440 x 2560",
         "tamaño": "453 KB",
         "fecha": "18 dic. 2016"   
       },
       
        {
         "author": "BossLogic",
         "url": "https://raw.githubusercontent.com/EdzonDM/InsWall-Walls/master/Colecciones/Heroes/Jubilee.png",
         "name": "Jubilee",
         "thumbnail": "https://raw.githubusercontent.com/EdzonDM/InsWall-Walls/master/Colecciones/Heroes/Preview/Jubilee%20Preview.jpg",
         "website": "https://www.behance.net/gallery/37661063/PopHead-Shots",
         "categoria": "Hero",
         "resolucion": "1440 x 2560",
         "tamaño": "194 KB",
         "fecha": "18 dic. 2016"   
       } ,      
       
       {
         "author": "BossLogic",
         "url": "https://raw.githubusercontent.com/EdzonDM/InsWall-Walls/master/Colecciones/Heroes/Deathstorm.png",
         "name": "Deathstorm",
         "thumbnail": "https://raw.githubusercontent.com/EdzonDM/InsWall-Walls/master/Colecciones/Heroes/Preview/Deathstorm%20Preview.jpg",
         "website": "https://www.behance.net/gallery/37661063/PopHead-Shots",
         "categoria": "Hero",
         "resolucion": "1440 x 2560",
         "tamaño": "213 KB",
         "fecha": "18 dic. 2016"   
       },        
       
        {
         "author": "BossLogic",
         "url": "https://raw.githubusercontent.com/EdzonDM/InsWall-Walls/master/Colecciones/Heroes/Reaper.png",
         "name": "Reaper",
         "thumbnail": "https://raw.githubusercontent.com/EdzonDM/InsWall-Walls/master/Colecciones/Heroes/Preview/Reaper%20Preview.jpg",
         "website": "https://www.behance.net/gallery/37661063/PopHead-Shots",
         "categoria": "Hero",
         "resolucion": "1440 x 2560",
         "tamaño": "167 KB",
         "fecha": "18 dic. 2016"   
       } , 
       
       {
         "author": "BossLogic",
         "url": "https://raw.githubusercontent.com/EdzonDM/InsWall-Walls/master/Colecciones/Heroes/Gray%20Fox.png",
         "name": "Gray Fox",
         "thumbnail": "https://raw.githubusercontent.com/EdzonDM/InsWall-Walls/master/Colecciones/Heroes/Preview/Gray%20Fox%20Preview.jpg",
         "website": "https://www.behance.net/gallery/37661063/PopHead-Shots",
         "categoria": "Hero",
         "resolucion": "1440 x 2560",
         "tamaño": "182 KB",
         "fecha": "18 dic. 2016"   
       },    
       
        {
         "author": "BossLogic",
         "url": "https://raw.githubusercontent.com/EdzonDM/InsWall-Walls/master/Colecciones/Heroes/Captain%20Hydra.png",
         "name": "Captain Hydra",
         "thumbnail": "https://raw.githubusercontent.com/EdzonDM/InsWall-Walls/master/Colecciones/Heroes/Preview/Captain%20Hydra%20Preview.jpg",
         "website": "https://www.behance.net/gallery/37661063/PopHead-Shots",
         "categoria": "Hero",
         "resolucion": "1440 x 2560",
         "tamaño": "215 KB",
         "fecha": "18 dic. 2016"   
       },
       
        {
         "author": "BossLogic",
         "url": "https://raw.githubusercontent.com/EdzonDM/InsWall-Walls/master/Colecciones/Heroes/The%20Flash.png",
         "name": "The Flash",
         "thumbnail": "https://raw.githubusercontent.com/EdzonDM/InsWall-Walls/master/Colecciones/Heroes/Preview/The%20Flash%20Preview.jpg",
         "website": "https://www.behance.net/gallery/37661063/PopHead-Shots",
         "categoria": "Hero",
         "resolucion": "1440 x 2560",
         "tamaño": "221 KB",
         "fecha": "18 dic. 2016"   
       } , 
       
        {
         "author": "BossLogic",
         "url": "https://raw.githubusercontent.com/EdzonDM/InsWall-Walls/master/Colecciones/Heroes/Doctor%20Doom.png",
         "name": "Doctor Doom",
         "thumbnail": "https://raw.githubusercontent.com/EdzonDM/InsWall-Walls/master/Colecciones/Heroes/Preview/Doctor%20Doom%20Preview.jpg",
         "website": "https://www.behance.net/gallery/37661063/PopHead-Shots",
         "categoria": "Hero",
         "resolucion": "1440 x 2560",
         "tamaño": "188 KB",
         "fecha": "18 dic. 2016"   
       } ,      
       
       {
         "author": "BossLogic",
         "url": "https://raw.githubusercontent.com/EdzonDM/InsWall-Walls/master/Colecciones/Heroes/Black%20Racer.png",
         "name": "Black Racer",
         "thumbnail": "https://raw.githubusercontent.com/EdzonDM/InsWall-Walls/master/Colecciones/Heroes/Preview/Black%20Racer%20Preview.jpg",
         "website": "https://www.behance.net/gallery/37661063/PopHead-Shots",
         "categoria": "Hero",
         "resolucion": "1440 x 2560",
         "tamaño": "212 KB",
         "fecha": "18 dic. 2016"   
       },    
             
       
       {
         "author": "BossLogic",
         "url": "https://raw.githubusercontent.com/EdzonDM/InsWall-Walls/master/Colecciones/Heroes/Batman%20Beyond.png",
         "name": "Batman Beyond",
         "thumbnail": "https://raw.githubusercontent.com/EdzonDM/InsWall-Walls/master/Colecciones/Heroes/Preview/Batman%20Beyond%20Preview.jpg",
         "website": "https://www.behance.net/gallery/37661063/PopHead-Shots",
         "categoria": "Hero",
         "resolucion": "1440 x 2560",
         "tamaño": "168 KB",
         "fecha": "18 dic. 2016"   
       } ,      
       
       {
         "author": "BossLogic",
         "url": "https://raw.githubusercontent.com/EdzonDM/InsWall-Walls/master/Colecciones/Heroes/Batman%202.png",
         "name": "Batman 2",
         "thumbnail": "https://raw.githubusercontent.com/EdzonDM/InsWall-Walls/master/Colecciones/Heroes/Preview/Batman%202%20Preview.jpg",
         "website": "https://www.behance.net/gallery/37661063/PopHead-Shots",
         "categoria": "Hero",
         "resolucion": "1440 x 2560",
         "tamaño": "174 KB",
         "fecha": "18 dic. 2016"   
       },        
       
        {
         "author": "BossLogic",
         "url": "https://raw.githubusercontent.com/EdzonDM/InsWall-Walls/master/Colecciones/Heroes/Winter%20Soldier.png",
         "name": "Winter Soldier",
         "thumbnail": "https://raw.githubusercontent.com/EdzonDM/InsWall-Walls/master/Colecciones/Heroes/Preview/Winter%20Soldier%20Preview.jpg",
         "website": "https://www.behance.net/gallery/37661063/PopHead-Shots",
         "categoria": "Hero",
         "resolucion": "1440 x 2560",
         "tamaño": "221 KB",
         "fecha": "18 dic. 2016"   
       } ,
       
       {
         "author": "BossLogic",
         "url": "https://raw.githubusercontent.com/EdzonDM/InsWall-Walls/master/Colecciones/Heroes/Zoom.png",
         "name": "Zoom",
         "thumbnail": "https://raw.githubusercontent.com/EdzonDM/InsWall-Walls/master/Colecciones/Heroes/Preview/Zoom%20Preview.jpg",
         "website": "https://www.behance.net/gallery/37661063/PopHead-Shots",
         "categoria": "Hero",
         "resolucion": "1440 x 2560",
         "tamaño": "208 KB",
         "fecha": "18 dic. 2016"   
       },
    
       {
         "author": "BossLogic",
         "url": "https://raw.githubusercontent.com/EdzonDM/InsWall-Walls/master/Colecciones/Heroes/Spider%20Man.png",
         "name": "Spider Man",
         "thumbnail": "https://raw.githubusercontent.com/EdzonDM/InsWall-Walls/master/Colecciones/Heroes/Preview/Spider%20Man%20Preview.jpg",
         "website": "https://www.behance.net/gallery/37661063/PopHead-Shots",
         "categoria": "Hero",
         "resolucion": "1440 x 2560",
         "tamaño": "233 KB",
         "fecha": "18 dic. 2016"   
       },        
       
       {
         "author": "BossLogic",
         "url": "https://raw.githubusercontent.com/EdzonDM/InsWall-Walls/master/Colecciones/Heroes/Reverse%20Flash.png",
         "name": "Reverse Flash",
         "thumbnail": "https://raw.githubusercontent.com/EdzonDM/InsWall-Walls/master/Colecciones/Heroes/Preview/Reverse%20Flash%20Preview.jpg",
         "website": "https://www.behance.net/gallery/37661063/PopHead-Shots",
         "categoria": "Hero",
         "resolucion": "1440 x 2560",
         "tamaño": "220 KB",
         "fecha": "18 dic. 2016"   
       },        
       
       {
         "author": "BossLogic",
         "url": "https://raw.githubusercontent.com/EdzonDM/InsWall-Walls/master/Colecciones/Heroes/Magneto.png",
         "name": "Magneto",
         "thumbnail": "https://raw.githubusercontent.com/EdzonDM/InsWall-Walls/master/Colecciones/Heroes/Preview/Magneto%20Preview.jpg",
         "website": "https://www.behance.net/gallery/37661063/PopHead-Shots",
         "categoria": "Hero",
         "resolucion": "1440 x 2560",
         "tamaño": "195 KB",
         "fecha": "18 dic. 2016"   
       },    
       
       {
         "author": "BossLogic",
         "url": "https://raw.githubusercontent.com/EdzonDM/InsWall-Walls/master/Colecciones/Heroes/Iron%20Man.png",
         "name": "Iron Man",
         "thumbnail": "https://raw.githubusercontent.com/EdzonDM/InsWall-Walls/master/Colecciones/Heroes/Preview/Iron%20Man2%20Preview.jpg",
         "website": "https://www.behance.net/gallery/37661063/PopHead-Shots",
         "categoria": "Hero",
         "resolucion": "1440 x 2560",
         "tamaño": "233 KB",
         "fecha": "18 dic. 2016"   
       },
       
       {
         "author": "BossLogic",
         "url": "https://raw.githubusercontent.com/EdzonDM/InsWall-Walls/master/Colecciones/Heroes/Deadpool.png",
         "name": "Deadpool",
         "thumbnail": "https://raw.githubusercontent.com/EdzonDM/InsWall-Walls/master/Colecciones/Heroes/Preview/Deadpool2%20Preview.jpg",
         "website": "https://www.behance.net/gallery/37661063/PopHead-Shots",
         "categoria": "Hero",
         "resolucion": "1440 x 2560",
         "tamaño": "246 KB",
         "fecha": "18 dic. 2016"   
       } ,  
       
        {
         "author": "BossLogic",
         "url": "https://raw.githubusercontent.com/EdzonDM/InsWall-Walls/master/Colecciones/Heroes/Green%20Arrow.png",
         "name": "Green Arrow",
         "thumbnail": "https://raw.githubusercontent.com/EdzonDM/InsWall-Walls/master/Colecciones/Heroes/Preview/Green%20Arrow%20Preview.jpg",
         "website": "https://www.behance.net/gallery/37661063/PopHead-Shots",
         "categoria": "Hero",
         "resolucion": "1440 x 2560",
         "tamaño": "194 KB",
         "fecha": "18 dic. 2016"   
       },    
       
       {
         "author": "BossLogic",
         "url": "https://raw.githubusercontent.com/EdzonDM/InsWall-Walls/master/Colecciones/Heroes/Captain%20America.png",
         "name": "Captain America",
         "thumbnail": "https://raw.githubusercontent.com/EdzonDM/InsWall-Walls/master/Colecciones/Heroes/Preview/Captain%20America%20Preview.jpg",
         "website": "https://www.behance.net/gallery/37661063/PopHead-Shots",
         "categoria": "Hero",
         "resolucion": "1440 x 2560",
         "tamaño": "245 KB",
         "fecha": "18 dic. 2016"   
       },    
             
       
       {
         "author": "BossLogic",
         "url": "https://raw.githubusercontent.com/EdzonDM/InsWall-Walls/master/Colecciones/Heroes/Black%20Flash.png",
         "name": "Black Flash",
         "thumbnail": "https://raw.githubusercontent.com/EdzonDM/InsWall-Walls/master/Colecciones/Heroes/Preview/Black%20Flash%20Preview.jpg",
         "website": "https://www.behance.net/gallery/37661063/PopHead-Shots",
         "categoria": "Hero",
         "resolucion": "1440 x 2560",
         "tamaño": "212 KB",
         "fecha": "18 dic. 2016"   
       } ,      
       
       {
         "author": "BossLogic",
         "url": "https://raw.githubusercontent.com/EdzonDM/InsWall-Walls/master/Colecciones/Heroes/Batman.png",
         "name": "Batman",
         "thumbnail": "https://raw.githubusercontent.com/EdzonDM/InsWall-Walls/master/Colecciones/Heroes/Preview/Batman2%20Preview.jpg",
         "website": "https://www.behance.net/gallery/37661063/PopHead-Shots",
         "categoria": "Hero",
         "resolucion": "1440 x 2560",
         "tamaño": "178 KB",
         "fecha": "18 dic. 2016"   
       },    
       
       {
         "author": "BossLogic",
         "url": "https://raw.githubusercontent.com/EdzonDM/InsWall-Walls/master/Colecciones/Heroes/Antman.png",
         "name": "Antman",
         "thumbnail": "https://raw.githubusercontent.com/EdzonDM/InsWall-Walls/master/Colecciones/Heroes/Preview/Antman%20Preview.jpg",
         "website": "https://www.behance.net/gallery/37661063/PopHead-Shots",
         "categoria": "Hero",
         "resolucion": "1440 x 2560",
         "tamaño": "305 KB",
         "fecha": "18 dic. 2016"   
       },
       
       {
         "author": "BossLogic",
         "url": "https://raw.githubusercontent.com/EdzonDM/InsWall-Walls/master/Colecciones/Heroes/Chibi%20Deadpool.jpg",
         "name": "Chibi Deadpool",
         "thumbnail": "https://raw.githubusercontent.com/EdzonDM/InsWall-Walls/master/Colecciones/Heroes/Preview/Chibi%20Deadpool%20Preview.jpg",
         "website": "",
         "categoria": "Hero",
         "resolucion": "1080 x 1920",
         "tamaño": "379 KB",
         "fecha": "18 dic. 2016"   
       } ,      
       
       {
         "author": "BossLogic",
         "url": "https://raw.githubusercontent.com/EdzonDM/InsWall-Walls/master/Colecciones/Heroes/Chibi%20Captain%20America.jpg",
         "name": "Chibi Captain",
         "thumbnail": "https://raw.githubusercontent.com/EdzonDM/InsWall-Walls/master/Colecciones/Heroes/Preview/Chibi%20Captain%20America%20Preview.jpg",
         "website": "",
         "categoria": "Hero",
         "resolucion": "1080 x 1920",
         "tamaño": "377 KB",
         "fecha": "18 dic. 2016"   
       },     
       
       {
         "author": "BossLogic",
         "url": "https://raw.githubusercontent.com/EdzonDM/InsWall-Walls/master/Colecciones/Heroes/Chibi%20Batman.jpg",
         "name": "Chibi Batman",
         "thumbnail": "https://raw.githubusercontent.com/EdzonDM/InsWall-Walls/master/Colecciones/Heroes/Preview/Chibi%20Batman%20Preview.jpg",
         "website": "",
         "categoria": "Hero",
         "resolucion": "1080 x 1920",
         "tamaño": "346 KB",
         "fecha": "18 dic. 2016"   
       },   
       
        {
         "author": "BossLogic",
         "url": "https://raw.githubusercontent.com/EdzonDM/InsWall-Walls/master/Colecciones/Heroes/Chibi%20Wolverine.jpg",
         "name": "Chibi Wolverine",
         "thumbnail": "https://raw.githubusercontent.com/EdzonDM/InsWall-Walls/master/Colecciones/Heroes/Preview/Chibi%20Wolverine%20Preview.jpg",
         "website": "",
         "categoria": "Hero",
         "resolucion": "1080 x 1920",
         "tamaño": "382 KB",
         "fecha": "18 dic. 2016"   
       } , 
       

       {
         "author": "BossLogic",
         "url": "https://raw.githubusercontent.com/EdzonDM/InsWall-Walls/master/Colecciones/Heroes/Chibi%20Arrow.jpg",
         "name": "Chibi Arrow",
         "thumbnail": "https://raw.githubusercontent.com/EdzonDM/InsWall-Walls/master/Colecciones/Heroes/Preview/Chibi%20Arrow%20Preview.jpg",
         "website": "",
         "categoria": "Hero",
         "resolucion": "1080 x 1920",
         "tamaño": "366 KB",
         "fecha": "18 dic. 2016"   
       } ,
       
       {
         "author": "BossLogic",
         "url": "https://raw.githubusercontent.com/EdzonDM/InsWall-Walls/master/Colecciones/Heroes/Chibi%20Duende.jpg",
         "name": "Chibi Duende",
         "thumbnail": "https://raw.githubusercontent.com/EdzonDM/InsWall-Walls/master/Colecciones/Heroes/Preview/Chibi%20Duende%20Preview.jpg",
         "website": "",
         "categoria": "Hero",
         "resolucion": "1080 x 1920",
         "tamaño": "342 KB",
         "fecha": "18 dic. 2016"   
       }       
       
    ]
}